SRP/SRPAfterglow.py
SRP/SRPAstro.py
SRP/SRPCalFlux.data
SRP/SRPConstants.py
SRP/SRPFiles.py
SRP/SRPUtil.py
SRP/TimeAstro.py
SRP/TimeAstro_algs.py
SRP/__init__.py
SRP/SRPCatalogue/AGNOptRefStarsClass.py
SRP/SRPCatalogue/APASSClass.py
SRP/SRPCatalogue/AstroWiseStandardStarsClass.py
SRP/SRPCatalogue/BrightStarsClass.py
SRP/SRPCatalogue/CatalogueConstants.py
SRP/SRPCatalogue/GetSDSS.py
SRP/SRPCatalogue/GetVizierCat.py
SRP/SRPCatalogue/IGAIAClass.py
SRP/SRPCatalogue/NIRStandardStarsClass.py
SRP/SRPCatalogue/ParseVizierCat.py
SRP/SRPCatalogue/SDSSClass.py
SRP/SRPCatalogue/SimbadClass.py
SRP/SRPCatalogue/SimbadNameClass.py
SRP/SRPCatalogue/SkyBotClass.py
SRP/SRPCatalogue/SmithetalStandardStarsClass.py
SRP/SRPCatalogue/StetsonJohnsonStandardStarsClass.py
SRP/SRPCatalogue/TWOMASSClass.py
SRP/SRPCatalogue/USNOB1Class.py
SRP/SRPCatalogue/USNOClass.py
SRP/SRPCatalogue/__init__.py
SRP/SRPCatalogue/sqlcl.py
SRP/SRPData/AtmExtinction/CerroPachon.dat
SRP/SRPData/AtmExtinction/LaPalma.dat
SRP/SRPData/AtmExtinction/LaSilla.dat
SRP/SRPData/AtmExtinction/MaunaKea.dat
SRP/SRPData/AtmExtinction/Paranal.dat
SRP/SRPData/Catalogues/AGNOptRefStars/AGNOPTSTD.txt
SRP/SRPData/Catalogues/AstroWiseStandardStars/cal569E_v11.fits
SRP/SRPData/Catalogues/BrightStarCatalogue/BrightStars.dat
SRP/SRPData/Catalogues/NIRCatalogueCollection/JohnsonSystem/NIRSTD.txt
SRP/SRPData/Catalogues/SmithetalStandardStars/smithetalugrizcat.dat
SRP/SRPData/Catalogues/StetsonStandardStars/JohnsonSystem/StetsonStandardStars.dat
SRP/SRPData/ESOEclipse/jitter.txt
SRP/SRPData/RefractiveIndex/METALS_Aluminium_Rakic.csv
SRP/SRPDatabases/__init__.py
SRP/SRPDatabases/readMySQLTable.py
SRP/SRPDatabases/readPostgresTable.py
SRP/SRPMath/AngleRange.py
SRP/SRPMath/AngularDistance.py
SRP/SRPMath/AstroAngleInput.py
SRP/SRPMath/AstroCoordInput.py
SRP/SRPMath/AstroMagInput.py
SRP/SRPMath/BiGauss.py
SRP/SRPMath/CartesianCoordAmpRotoTranslation.py
SRP/SRPMath/CartesianDistance.py
SRP/SRPMath/CartesianVectorClass.py
SRPAstro-4.9.0.dist-info/LICENSE.txt
SRPAstro-4.9.0.dist-info/METADATA
SRPAstro-4.9.0.dist-info/WHEEL
SRPAstro-4.9.0.dist-info/top_level.txt
SRPAstro-4.9.0.dist-info/RECORD
