Metadata-Version: 2.1
Name: SRPAstro
Version: 4.9.0
Summary: Astronomical Data Analysis Tools
Home-page: https://pypi.python.org/pypi/SRPAstro
Author: Stefano Covino
Author-email: stefano.covino@inaf.it
Keywords: astronomy data analysis
Classifier: Development Status :: 5 - Production/Stable
Classifier: Environment :: Console
Classifier: Intended Audience :: Science/Research
Classifier: Topic :: Scientific/Engineering :: Astronomy
Classifier: License :: OSI Approved :: MIT License
Classifier: Operating System :: MacOS :: MacOS X
Classifier: Operating System :: Unix
Classifier: Operating System :: POSIX
Classifier: Programming Language :: Python :: 3
Requires-Python: >=3
License-File: LICENSE.txt
Requires-Dist: AstroAtmosphere
Requires-Dist: mysql-connector-python
Requires-Dist: py-postgresql
Requires-Dist: requests
Requires-Dist: astroquery
Requires-Dist: astropy >=0.4
Requires-Dist: scipy
Requires-Dist: astlib >=0.4
Requires-Dist: matplotlib
Requires-Dist: atpy
Requires-Dist: ephem
Requires-Dist: numpy >=1.1
Requires-Dist: dust-extinction
